MT5Manager/MT5APIManager64.dll
MT5Manager/__init__.py
MT5Manager/_core.cp310-win_amd64.pdb
MT5Manager/_core.cp310-win_amd64.pyd
MT5Manager/_core.pyi
mt5manager-5.0.5572.dist-info/LICENSE.txt
mt5manager-5.0.5572.dist-info/METADATA
mt5manager-5.0.5572.dist-info/WHEEL
mt5manager-5.0.5572.dist-info/top_level.txt
mt5manager-5.0.5572.dist-info/RECORD
