Metadata-Version: 2.1
Name: mt5manager
Version: 5.0.5572
Summary: MetaTrader 5 Manager API
Home-page: https://www.metatrader5.com
Author: MetaQuotes Ltd.
Author-email: plugins@metaquotes.net
Maintainer: MetaQuotes Ltd.
Maintainer-email: plugins@metaquotes.net
License: MIT
Project-URL: Documentation, https://support.metaquotes.net
Keywords: metatrader manager api trading platform mt5 metaquotes forex currency exchange
Platform: Windows
Classifier: Development Status :: 5 - Production/Stable
Classifier: Topic :: Office/Business :: Financial
Classifier: License :: OSI Approved :: MIT License
Classifier: Programming Language :: Python :: 3.7
Classifier: Programming Language :: Python :: 3.8
Classifier: Programming Language :: Python :: 3.9
Classifier: Programming Language :: Python :: 3.10
Classifier: Programming Language :: Python :: 3.11
Classifier: Programming Language :: Python :: 3.12
Classifier: Programming Language :: Python :: 3.13
Classifier: Programming Language :: Python :: 3.14
Requires-Python: >=3.7, <4
License-File: LICENSE.txt
Requires-Dist: numpy>=1.7
